sphinx_social/__init__.py
sphinx_social-0.0.0.dist-info/METADATA
sphinx_social-0.0.0.dist-info/WHEEL
sphinx_social-0.0.0.dist-info/top_level.txt
sphinx_social-0.0.0.dist-info/RECORD
